monic/F2.py
monic/__init__.py
monic-0.4.dist-info/METADATA
monic-0.4.dist-info/WHEEL
monic-0.4.dist-info/top_level.txt
monic-0.4.dist-info/RECORD
