Metadata-Version: 2.1
Name: monic
Version: 0.4
Summary: This is monotonic
Home-page: https://github.com/std
Author: K Antonov
Author-email: kirill_antonov1111@mail.ru
License: BSD 2-clause
Platform: UNKNOWN
